{"frames": {

"ground.png":
{
	"frame": {"x":0,"y":0,"w":64,"h":64},
	"rotated": false,
	"trimmed": false,
	"spriteSourceSize": {"x":0,"y":0,"w":64,"h":64},
	"sourceSize": {"w":64,"h":64}
},
"wood.png":
{
	"frame": {"x":64,"y":0,"w":64,"h":64},
	"rotated": false,
	"trimmed": false,
	"spriteSourceSize": {"x":0,"y":0,"w":64,"h":64},
	"sourceSize": {"w":64,"h":64}
},
"wood_l.png":
{
	"frame": {"x":128,"y":0,"w":64,"h":64},
	"rotated": false,
	"trimmed": false,
	"spriteSourceSize": {"x":0,"y":0,"w":64,"h":64},
	"sourceSize": {"w":64,"h":64}
},
"wood_r.png":
{
	"frame": {"x":192,"y":0,"w":64,"h":64},
	"rotated": false,
	"trimmed": false,
	"spriteSourceSize": {"x":0,"y":0,"w":64,"h":64},
	"sourceSize": {"w":64,"h":64}
}},
"meta": {
	"app": "https://www.codeandweb.com/texturepacker",
	"version": "1.0",
	"image": "platforms.png",
	"format": "RGBA8888",
	"size": {"w":256,"h":64},
	"scale": "1",
	"smartupdate": "$TexturePacker:SmartUpdate:b99742c3373c30a90da9792186d309c6:17285800b8da957aea412efb54fb7d8b:f25efcec0d996575d4a89b4a2525a662$"
}
}
